<?xml version="1.0" encoding="utf-8" ?>
<SampleMetadata>
	<IsFullApplication>false</IsFullApplication>
	<Level>Advanced</Level>
	<Tags>Xamarin.Forms, Material</Tags>
	<SupportedPlatforms>Android, iOS</SupportedPlatforms>
	<LicenseRequirement>Indie</LicenseRequirement>
	<Gallery>true</Gallery>
	<Brief>Restaurant App is a sample open source application, powered by ASP.NET Core 2.1 and Xamarin.Forms 3.0. It incorporates material design and provides us with an overview of how to build mobile and web applications with a clean architecture and write testable and clean code.</Brief>
	<DownloadUrl>https://github.com/Jurabek/Restaurant-App/archive/develop.zip</DownloadUrl>
	<Author>Jurabek</Author>
</SampleMetadata>
